appwrite/__init__.py
appwrite/client.py
appwrite/exception.py
appwrite/id.py
appwrite/input_file.py
appwrite/operator.py
appwrite/permission.py
appwrite/query.py
appwrite/role.py
appwrite/service.py
appwrite/encoders/__init__.py
appwrite/encoders/value_class_encoder.py
appwrite/enums/__init__.py
appwrite/enums/adapter.py
appwrite/enums/attribute_status.py
appwrite/enums/authentication_factor.py
appwrite/enums/authenticator_type.py
appwrite/enums/browser.py
appwrite/enums/build_runtime.py
appwrite/enums/column_status.py
appwrite/enums/compression.py
appwrite/enums/credit_card.py
appwrite/enums/database_type.py
appwrite/enums/deployment_download_type.py
appwrite/enums/deployment_status.py
appwrite/enums/execution_method.py
appwrite/enums/execution_status.py
appwrite/enums/execution_trigger.py
appwrite/enums/flag.py
appwrite/enums/framework.py
appwrite/enums/health_antivirus_status.py
appwrite/enums/health_check_status.py
appwrite/enums/image_format.py
appwrite/enums/image_gravity.py
appwrite/enums/index_status.py
appwrite/enums/index_type.py
appwrite/enums/message_priority.py
appwrite/enums/message_status.py
appwrite/enums/messaging_provider_type.py
appwrite/enums/name.py
appwrite/enums/o_auth_provider.py
appwrite/enums/password_hash.py
appwrite/enums/relation_mutate.py
appwrite/enums/relationship_type.py
appwrite/enums/runtime.py
appwrite/enums/smtp_encryption.py
appwrite/enums/vcs_deployment_type.py
appwrite/services/__init__.py
appwrite/services/account.py
appwrite/services/avatars.py
appwrite/services/databases.py
appwrite/services/functions.py
appwrite/services/graphql.py
appwrite/services/health.py
appwrite/services/locale.py
appwrite/services/messaging.py
appwrite/services/sites.py
appwrite/services/storage.py
appwrite/services/tables_db.py
appwrite/services/teams.py
appwrite/services/tokens.py
appwrite/services/users.py
appwrite/utils/__init__.py
appwrite/utils/deprecated.py
appwrite-13.6.1.dist-info/licenses/LICENSE
appwrite-13.6.1.dist-info/METADATA
appwrite-13.6.1.dist-info/WHEEL
appwrite-13.6.1.dist-info/top_level.txt
appwrite-13.6.1.dist-info/RECORD
