Metadata-Version: 2.4
Name: appwrite
Version: 13.6.1
Summary: Appwrite is an open-source self-hosted backend server that abstract and simplify complex and repetitive development tasks behind a very simple REST API
Home-page: https://appwrite.io/support
Download-URL: https://github.com/appwrite/sdk-for-python/archive/13.6.1.tar.gz
Author: Appwrite Team
Author-email: team@appwrite.io
Maintainer: Appwrite Team
Maintainer-email: team@appwrite.io
License: BSD-3-Clause
Classifier: Development Status :: 5 - Production/Stable
Classifier: Intended Audience :: Developers
Classifier: Environment :: Web Environment
Classifier: Topic :: Software Development
Classifier: License :: OSI Approved :: BSD License
Classifier: Programming Language :: Python :: 3
Classifier: Programming Language :: Python :: 3.5
Classifier: Programming Language :: Python :: 3.6
Classifier: Programming Language :: Python :: 3.7
Classifier: Programming Language :: Python :: 3.8
License-File: LICENSE
Requires-Dist: requests
Dynamic: author
Dynamic: author-email
Dynamic: classifier
Dynamic: description
Dynamic: description-content-type
Dynamic: download-url
Dynamic: home-page
Dynamic: license
Dynamic: license-file
Dynamic: maintainer
Dynamic: maintainer-email
Dynamic: requires-dist
Dynamic: summary
